<annotation>
	<folder>images</folder>
	<filename>image(162).jpeg</filename>
	<path>C:\Users\yuzhe\Documents\GitHub\car_and_cones\data\images\image(162).jpeg</path>
	<source>
		<database>Unknown</database>
	</source>
	<size>
		<width>300</width>
		<height>168</height>
		<depth>3</depth>
	</size>
	<segmented>0</segmented>
	<object>
		<name>car</name>
		<pose>Unspecified</pose>
		<truncated>0</truncated>
		<difficult>0</difficult>
		<bndbox>
			<xmin>161</xmin>
			<ymin>66</ymin>
			<xmax>273</xmax>
			<ymax>151</ymax>
		</bndbox>
	</object>
	<object>
		<name>car</name>
		<pose>Unspecified</pose>
		<truncated>0</truncated>
		<difficult>0</difficult>
		<bndbox>
			<xmin>133</xmin>
			<ymin>80</ymin>
			<xmax>179</xmax>
			<ymax>127</ymax>
		</bndbox>
	</object>
	<object>
		<name>car</name>
		<pose>Unspecified</pose>
		<truncated>0</truncated>
		<difficult>0</difficult>
		<bndbox>
			<xmin>110</xmin>
			<ymin>78</ymin>
			<xmax>149</xmax>
			<ymax>118</ymax>
		</bndbox>
	</object>
</annotation>
